# JVM 指令

在 JVM 规范中定义了将近 200+ 个指令，如下表所示：

|  op  | 语法                                                   | 栈                                       | 描述                                                                              |
|:----:|--------------------------------------------------------|------------------------------------------|-----------------------------------------------------------------------------------|
| 0x00 |<em id="nop">nop</em>                                   |无变化                                    | 不执行任何操作                                                                    |
| 0x01 |<em id="aconst_null">aconst_null</em>                   |*... → ...,null*                          | 将 *null* 引用压入栈[^1]顶                                                        |
| 0x02 |<em id="iconst_m1">iconst_m1</em>                       |*... → ...,-1*                            | 将 *int* 常量值 *-1* 压入栈顶                                                     |
| 0x03 |<em id="iconst_0">iconst_0</em>                         |*..   . → ...,0*                          | 将 *int* 常量值 *0* 压入栈顶                                                      |
| 0x04 |<em id="iconst_1">iconst_1</em>                         |*... → ...,1*                             | 将 *int* 常量值 *1* 压入栈顶                                                      |
| 0x05 |<em id="iconst_2">iconst_2</em>                         |*... → ...,2*                             | 将 *int* 常量值 *2* 压入栈顶                                                      |
| 0x06 |<em id="iconst_3">iconst_3</em>                         |*... → ...,3*                             | 将 *int* 常量值 *3* 压入栈顶                                                      |
| 0x07 |<em id="iconst_4">iconst_4</em>                         |*... → ...,4*                             | 将 *int* 常量值 *4* 压入栈顶                                                      |
| 0x08 |<em id="iconst_5">iconst_5</em>                         |*... → ...,5*                             | 将 *int* 常量值 *5* 压入栈顶                                                      |
| 0x09 |<em id="lconst_0">lconst_0</em>                         |*... → ...,0L*                            | 将 *long* 常量值 *0L* 压入栈顶                                                    |
| 0x0a |<em id="lconst_1">lconst_1</em>                         |*... → ...,1L*                            | 将 *long* 常量值 *1L* 压入栈顶                                                    |
| 0x0b |<em id="fconst_0">fconst_0</em>                         |*... → ...,0.0f*                          | 将 *float* 常量值 *0.0f* 压入栈顶                                                 |
| 0x0c |<em id="fconst_1">fconst_1</em>                         |*... → ...,1.0f*                          | 将 *float* 常量值 *1.0f* 压入栈顶                                                 |
| 0x0d |<em id="fconst_2">fconst_2</em>                         |*... → ...,2.0f*                          | 将 *float* 常量值 *1.0f* 压入栈顶                                                 |
| 0x0e |<em id="dconst_0">dconst_0</em>                         |*... → ...,0.0*                           | 将 *double* 常量值 *0.0* 压入栈顶                                                 |
| 0x0f |<em id="dconst_1">dconst_1</em>                         |*... → ...,1.0*                           | 将 *double* 常量值 *1.0* 压入栈顶                                                 |
| 0x10 |<em id="bipush">bipush,AA[^2]</em>                      |*... → ...,v*                             | 将立即数[^3] *AA* 压入栈顶                                                        |
| 0x11 |<em id="sipush">sipush,AAAA[^4]</em>                    |*... → ...,v*                             | 将立即数 *AAAA* 压入栈顶                                                          |
| 0x12 |<em id="ldc">ldc,AA</em>                                |*... → ...,v*                             | 将常量池中索引为 *AA* 的常量压入栈顶                                              |
| 0x13 |<em id="ldc_w">ldc_w,AAAA</em>                          |*... → ...,v*                             | 将常量池中索引为 *AAAA* 的常量压入栈顶                                            |
| 0x14 |<em id="ldc2_w">ldc2_w,AAAA</em>                        |*... → ...,v*                             | 将常量池中索引为 *AAAA* 的 *long* 或 *double* 常量压入栈顶                        |
| 0x15 |<em id="iload">iload,AA</em>                            |*... → ...,v*                             | 将本地变量表中索引为 *AA* 的 *int* 变量压入栈顶                                   |
| 0x16 |<em id="lload">lload,AA</em>                            |*... → ...,v*                             | 将本地变量表中索引为 *AA* 的 *long* 变量压入栈顶                                  |
| 0x17 |<em id="fload">fload,AA</em>                            |*... → ...,v*                             | 将本地变量表中索引为 *AA* 的 *float* 变量压入栈顶                                 |
| 0x18 |<em id="dload">dload,AA</em>                            |*... → ...,v*                             | 将本地变量表中索引为 *AA* 的 *double* 变量压入栈顶                                |
| 0x19 |<em id="aload">aload,AA</em>                            |*... → ...,v*                             | 将本地变量表中索引为 *AA* 的 *aref* 压入栈顶                                      |
| 0x1a |<em id="iload_0">iload_0</em>                           |*... → ...,0*                             | 将本地变量表中索引为 *0* 的 *int* 变量压入栈顶                                    |
| 0x1b |<em id="iload_1">iload_1</em>                           |*... → ...,1*                             | 将本地变量表中索引为 *1* 的 *int* 变量压入栈顶                                    |
| 0x1c |<em id="iload_2">iload_2</em>                           |*... → ...,2*                             | 将本地变量表中索引为 *2* 的 *int* 变量压入栈顶                                    |
| 0x1d |<em id="iload_3">iload_3</em>                           |*... → ...,3*                             | 将本地变量表中索引为 *3* 的 *int* 变量压入栈顶                                    |
| 0x1e |<em id="lload_0">lload_0</em>                           |*... → ...,0L*                            | 将本地变量表中索引为 *0* 的 *long* 变量压入栈顶                                   |
| 0x1f |<em id="lload_1">lload_1</em>                           |*... → ...,1L*                            | 将本地变量表中索引为 *1* 的 *long* 变量压入栈顶                                   |
| 0x20 |<em id="lload_2">lload_2</em>                           |*... → ...,2L*                            | 将本地变量表中索引为 *2* 的 *long* 变量压入栈顶                                   |
| 0x21 |<em id="lload_3">lload_3</em>                           |*... → ...,3L*                            | 将本地变量表中索引为 *3* 的 *long* 变量压入栈顶                                   |
| 0x22 |<em id="fload_0">fload_0</em>                           |*... → ...,0.0f*                          | 将本地变量表中索引为 *0* 的 *float* 变量压入栈顶                                  |
| 0x23 |<em id="fload_1">fload_1</em>                           |*... → ...,1.0f*                          | 将本地变量表中索引为 *1* 的 *float* 变量压入栈顶                                  |
| 0x24 |<em id="fload_2">fload_2</em>                           |*... → ...,2.0f*                          | 将本地变量表中索引为 *2* 的 *float* 变量压入栈顶                                  |
| 0x25 |<em id="fload_3">fload_3</em>                           |*... → ...,3.0f*                          | 将本地变量表中索引为 *3* 的 *float* 变量压入栈顶                                  |
| 0x26 |<em id="dload_0">dload_0</em>                           |*... → ...,0.0*                           | 将本地变量表中索引为 *0* 的 *double* 变量压入栈顶                                 |
| 0x27 |<em id="dload_1">dload_1</em>                           |*... → ...,1.0*                           | 将本地变量表中索引为 *1* 的 *double* 变量压入栈顶                                 |
| 0x28 |<em id="dload_2">dload_2</em>                           |*... → ...,2.0*                           | 将本地变量表中索引为 *2* 的 *double* 变量压入栈顶                                 |
| 0x29 |<em id="dload_3">dload_3</em>                           |*... → ...,3.0*                           | 将本地变量表中索引为 *3* 的 *double* 变量压入栈顶                                 |
| 0x2a |<em id="aload_0">aload_0</em>                           |*... → ...,aref*                          | 将本地变量表中索引为 *0* 的 *aref* 压入栈顶                                       |
| 0x2b |<em id="aload_1">aload_1</em>                           |*... → ...,aref*                          | 将本地变量表中索引为 *1* 的 *aref* 压入栈顶                                       |
| 0x2c |<em id="aload_2">aload_2</em>                           |*... → ...,aref*                          | 将本地变量表中索引为 *2* 的 *aref* 压入栈顶                                       |
| 0x2d |<em id="aload_3">aload_3</em>                           |*... → ...,aref*                          | 将本地变量表中索引为 *3* 的 *aref* 压入栈顶                                       |
| 0x2e |<em id="iaload">iaload*</em>                            |*...,aaref,index → ...,v*                 | 将数组 *aaref* 中索引为 *index (int)* 的 *int* 值压入栈顶                         |
| 0x2f |<em id="laload">laload</em>                             |*...,aaref,index → ...,v*                 | 将数组 *aaref* 中索引为 *index (int)* 的 *long* 值压入栈顶                        |
| 0x30 |<em id="faload">faload</em>                             |*...,aaref,index → ...,v*                 | 将数组 *aaref* 中索引为 *index (int)* 的 *float* 值压入栈顶                       |
| 0x31 |<em id="daload">daload</em>                             |*...,aaref,index → ...,v*                 | 将数组 *aaref* 中索引为 *index (int)* 的 *double* 值压入栈顶                      |
| 0x32 |<em id="aaload">aaload</em>                             |*...,aaref,index → ...,v*                 | 将数组 *aaref* 中索引为 *index (int)* 的 *reference* 值压入栈顶                   |
| 0x33 |<em id="baload">baload</em>                             |*...,aaref,index → ...,v*                 | 将数组 *aaref* 中索引为 *index (int)* 的 *byte* 或 *boolean* 值压入栈顶           |
| 0x34 |<em id="caload">caload</em>                             |*...,aaref,index → ...,v*                 | 将数组 *aaref* 中索引为 *index (int)* 的 *char* 值压入栈顶                        |
| 0x35 |<em id="saload">saload</em>                             |*...,aaref,index → ...,v*                 | 将数组 *aaref* 中索引为 *index (int)* 的 *short* 值压入栈顶                       |
| 0x36 |<em id="istore">istore,AA</em>                          |*...,v → ...,*                            | 将 *int* 值从栈顶弹出，并赋值给本地变量表中索引为 *AA* 的本地变量                 |
| 0x37 |<em id="lstore">lstore,AA</em>                          |*...,v → ...,*                            | 将 *long* 值从栈顶弹出，并赋值给本地变量表中索引为 *AA* 的本地变量                |
| 0x38 |<em id="fstore">fstore,AA</em>                          |*...,v → ...,*                            | 将 *float* 值从栈顶弹出，并赋值给本地变量表中索引为 *AA* 的本地变量               |
| 0x39 |<em id="dstore">dstore,AA</em>                          |*...,v → ...,*                            | 将 *double* 值从栈顶弹出，并赋值给本地变量表中索引为 *AA* 的本地变量              |
| 0x3a |<em id="astore">astore,AA</em>                          |*...,v → ...,*                            | 将 *reference* 值从栈顶弹出，并赋值给本地变量表中索引为 *AA* 的本地变量           |
| 0x3b |<em id="istore_0">istore_0</em>                         |*...,v → ...,*                            | 将 *int* 值从栈顶弹出，并赋值给本地变量表中索引为 *0* 的本地变量                  |
| 0x3c |<em id="istore_1">istore_1</em>                         |*...,v → ...,*                            | 将 *int* 值从栈顶弹出，并赋值给本地变量表中索引为 *1* 的本地变量                  |
| 0x3d |<em id="istore_2">istore_2</em>                         |*...,v → ...,*                            | 将 *int* 值从栈顶弹出，并赋值给本地变量表中索引为 *2* 的本地变量                  |
| 0x3e |<em id="istore_3">istore_3</em>                         |*...,v → ...,*                            | 将 *int* 值从栈顶弹出，并赋值给本地变量表中索引为 *3* 的本地变量                  |
| 0x3f |<em id="lstore_0">lstore_0</em>                         |*...,v → ...,*                            | 将 *long* 值从栈顶弹出，并赋值给本地变量表中索引为 *0* 的本地变量                 |
| 0x40 |<em id="lstore_1">lstore_1</em>                         |*...,v → ...,*                            | 将 *long* 值从栈顶弹出，并赋值给本地变量表中索引为 *1* 的本地变量                 |
| 0x41 |<em id="lstore_2">lstore_2</em>                         |*...,v → ...,*                            | 将 *long* 值从栈顶弹出，并赋值给本地变量表中索引为 *2* 的本地变量                 |
| 0x42 |<em id="lstore_3">lstore_3</em>                         |*...,v → ...,*                            | 将 *long* 值从栈顶弹出，并赋值给本地变量表中索引为 *3* 的本地变量                 |
| 0x43 |<em id="fstore_0">fstore_0</em>                         |*...,v → ...,*                            | 将 *float* 值从栈顶弹出，并赋值给本地变量表中索引为 *0* 的本地变量                |
| 0x44 |<em id="fstore_1">fstore_1</em>                         |*...,v → ...,*                            | 将 *float* 值从栈顶弹出，并赋值给本地变量表中索引为 *1* 的本地变量                |
| 0x45 |<em id="fstore_2">fstore_2</em>                         |*...,v → ...,*                            | 将 *float* 值从栈顶弹出，并赋值给本地变量表中索引为 *2* 的本地变量                |
| 0x46 |<em id="fstore_3">fstore_3</em>                         |*...,v → ...,*                            | 将 *float* 值从栈顶弹出，并赋值给本地变量表中索引为 *3* 的本地变量                |
| 0x47 |<em id="dstore_0">dstore_0</em>                         |*...,v → ...,*                            | 将 *double* 值从栈顶弹出，并赋值给本地变量表中索引为 *0* 的本地变量               |
| 0x48 |<em id="dstore_1">dstore_1</em>                         |*...,v → ...,*                            | 将 *double* 值从栈顶弹出，并赋值给本地变量表中索引为 *1* 的本地变量               |
| 0x49 |<em id="dstore_2">dstore_2</em>                         |*...,v → ...,*                            | 将 *double* 值从栈顶弹出，并赋值给本地变量表中索引为 *2* 的本地变量               |
| 0x4a |<em id="dstore_3">dstore_3</em>                         |*...,v → ...,*                            | 将 *double* 值从栈顶弹出，并赋值给本地变量表中索引为 *3* 的本地变量               |
| 0x4b |<em id="astore_0">astore_0</em>                         |*...,aref → ...,*                         | 将 *reference* 值从栈顶弹出，并赋值给本地变量表中索引为 *0* 的本地变量            |
| 0x4c |<em id="astore_1">astore_1</em>                         |*...,aref → ...,*                         | 将 *reference* 值从栈顶弹出，并赋值给本地变量表中索引为 *1* 的本地变量            |
| 0x4d |<em id="astore_2">astore_2</em>                         |*...,aref → ...,*                         | 将 *reference* 值从栈顶弹出，并赋值给本地变量表中索引为 *2* 的本地变量            |
| 0x4e |<em id="astore_3">astore_3</em>                         |*...,aref → ...,*                         | 将 *reference* 值从栈顶弹出，并赋值给本地变量表中索引为 *3* 的本地变量            |
| 0x4f |<em id="iastore">iastore</em>                           |*...,aaref,index,v → ...,*                | 将 *aaref, index (int), v (int)* 从栈顶弹出，并将 *v* 存入 *aaref[index]*         |
| 0x50 |<em id="lastore">lastore</em>                           |*...,aaref,index,v → ...,*                | 将 *aaref, index (int), v (long)* 从栈顶弹出，并将 *v* 存入 *aaref[index]*        |
| 0x51 |<em id="fastore">fastore</em>                           |*...,aaref,index,v → ...,*                | 将 *aaref, index (int), v (float)* 从栈顶弹出，并将 *v* 存入 *aaref[index]*       |
| 0x52 |<em id="dastore">dastore</em>                           |*...,aaref,index,v → ...,*                | 将 *aaref, index (int), v (double)* 从栈顶弹出，并将 *v* 存入 *aaref[index]*      |
| 0x53 |<em id="aastore">aastore</em>                           |*...,aaref,index,v → ...,*                | 将 *aaref, index (int), v (reference)* 从栈顶弹出，并将 *v* 存入 *aaref[index]*   |
| 0x54 |<em id="bastore">bastore</em>                           |*...,aaref,index,v → ...,*                | 将 *aaref, index (int), v (byte)* 从栈顶弹出，并将 *v* 存入 *aaref[index]*        |
| 0x55 |<em id="castore">castore</em>                           |*...,aaref,index,v → ...,*                | 将 *aaref, index (int), v (char)* 从栈顶弹出，并将 *v* 存入 *aaref[index]*        |
| 0x56 |<em id="sastore">sastore</em>                           |*...,aaref,index,v → ...,*                | 将 *aaref, index (int), v (short)* 从栈顶弹出，并将 *v* 存入 *aaref[index]*       |
| 0x57 |<em id="pop">pop</em>                                   |*...,v → ...,*                            | 将栈顶的值弹出                                                                    |
| 0x58 |<em id="pop2">pop2</em>                                 |*...,v2,v1 → ...,*                        | 将栈顶的 1 或 2 个值弹出                                                          |
| 0x59 |<em id="dup">dup</em>                                   |*...,v → ...,v,v*                         | 复制栈顶的值，并将复制的值压入栈顶                                                |
| 0x5a |<em id="dup_x1">dup_x1</em>                             |*...,v2,v1 → ...,v1,v2,v1*                | 复制栈顶的值，并将复制的值插在栈顶往下的第 2 个位置                               |
| 0x5b |<em id="dup_x2">dup_x2</em>                             |*...,v3,v2,v1 → ...,v1,v3,v2,v1*          | 复制栈顶的值，并将复制的值插在栈顶往下的第 2 或 3 个位置                          |
| 0x5c |<em id="dup2">dup2</em>                                 |*...,v2,v1 → ...,v2,v1,v2,v1*             | 复制栈顶的 1 或 2 个值，并将复制的值按原来的顺序压入栈顶                          |
| 0x5d |<em id="dup2_x1">dup2_x1</em>                           |*...,v3,v2,v1 → ...,v2,v1,v3,v2,v1*       | 复制栈顶的 1 或 2 个值，并将复制的值按原来的顺序插在栈顶往下的第 2 或 3个位置     |
| 0x5e |<em id="dup2_x2">dup2_x2</em>                           |*...,v4,v3,v2,v1 → ...,v2,v1,v4,v3,v2,v1* | 复制栈顶的 1 或 2 个值，并将复制的值按原来的顺序插在栈顶往下的第 2、3 或 4 个位置 |
| 0x5f |<em id="swap">swap</em>                                 |*...,v2,v1 → ...,v1,v2*                   | 交换栈顶的两个值                                                                  |
| 0x60 |<em id="iadd">iadd</em>                                 |*...,v1,v2 → ...,result*                  | 将栈顶的两个 *int* 值相加，并将结果压入栈顶                                       |
| 0x61 |<em id="ladd">ladd</em>                                 |*...,v1,v2 → ...,result*                  | 将栈顶的两个 *long* 值相加，并将结果压入栈顶                                      |
| 0x62 |<em id="fadd">fadd</em>                                 |*...,v1,v2 → ...,result*                  | 将栈顶的两个 *float* 值相加，并将结果压入栈顶                                     |
| 0x63 |<em id="dadd">dadd</em>                                 |*...,v1,v2 → ...,result*                  | 将栈顶的两个 *double* 值相加，并将结果压入栈顶                                    |
| 0x64 |<em id="isub">isub</em>                                 |*...,v1,v2 → ...,result*                  | 将栈顶的下一个 *int* 值减栈顶的 *int* 值，并将结果压入栈顶                        |
| 0x65 |<em id="lsub">lsub</em>                                 |*...,v1,v2 → ...,result*                  |                                                                                   |
| 0x66 |<em id="fsub">fsub</em>                                 |*...,v1,v2 → ...,result*                  |                                                                                   |
| 0x67 |<em id="dsub">dsub</em>                                 |*...,v1,v2 → ...,result*                  |                                                                                   |
| 0x68 |<em id="imul">imul</em>                                 |*...,v1,v2 → ...,result*                  |                                                                                   |
| 0x69 |<em id="lmul">lmul</em>                                 |*...,v1,v2 → ...,result*                  |                                                                                   |
| 0x6a |<em id="fmul">fmul</em>                                 |*...,v1,v2 → ...,result*                  |                                                                                   |
| 0x6b |<em id="dmul">dmul</em>                                 |*...,v1,v2 → ...,result*                  |                                                                                   |
| 0x6c |<em id="idiv">idiv</em>                                 |*...,v1,v2 → ...,result*                  |                                                                                   |
| 0x6d |<em id="ldiv">ldiv</em>                                 |*...,v1,v2 → ...,result*                  |                                                                                   |
| 0x6e |<em id="fdiv">fdiv</em>                                 |*...,v1,v2 → ...,result*                  |                                                                                   |
| 0x6f |<em id="ddiv">ddiv</em>                                 |*...,v1,v2 → ...,result*                  |                                                                                   |
| 0x70 |<em id="irem">irem</em>                                 |*...,v1,v2 → ...,result*                  |                                                                                   |
| 0x71 |<em id="lrem">lrem</em>                                 |*...,v1,v2 → ...,result*                  |                                                                                   |
| 0x72 |<em id="frem">frem</em>                                 |*...,v1,v2 → ...,result*                  |                                                                                   |
| 0x73 |<em id="drem">drem</em>                                 |*...,v1,v2 → ...,result*                  |                                                                                   |
| 0x74 |<em id="ineg">ineg</em>                                 |*...,v1,v2 → ...,result*                  |                                                                                   |
| 0x75 |<em id="lneg">lneg</em>                                 |*...,v1,v2 → ...,result*                  |                                                                                   |
| 0x76 |<em id="fneg">fneg</em>                                 |*...,v1,v2 → ...,result*                  |                                                                                   |
| 0x77 |<em id="dneg">dneg</em>                                 |*...,v1,v2 → ...,result*                  |                                                                                   |
| 0x78 |<em id="ishl">ishl</em>                                 |*...,v1,v2 → ...,result*                  |                                                                                   |
| 0x79 |<em id="lshl">lshl</em>                                 |*...,v1,v2 → ...,result*                  |                                                                                   |
| 0x7a |<em id="ishr">ishr</em>                                 |*...,v1,v2 → ...,result*                  |                                                                                   |
| 0x7b |<em id="lshr">lshr</em>                                 |*...,v1,v2 → ...,result*                  |                                                                                   |
| 0x7c |<em id="iushr">iushr</em>                               |*...,v1,v2 → ...,result*                  |                                                                                   |
| 0x7d |<em id="lushr">lushr</em>                               |*...,v1,v2 → ...,result*                  |                                                                                   |
| 0x7e |<em id="iand">iand</em>                                 |*...,v1,v2 → ...,result*                  |                                                                                   |
| 0x7f |<em id="land">land</em>                                 |*...,v1,v2 → ...,result*                  |                                                                                   |
| 0x80 |<em id="ior">ior</em>                                   |*...,v1,v2 → ...,result*                  |                                                                                   |
| 0x81 |<em id="lor">lor</em>                                   |*...,v1,v2 → ...,result*                  |                                                                                   |
| 0x82 |<em id="ixor">ixor</em>                                 |*...,v1,v2 → ...,result*                  |                                                                                   |
| 0x83 |<em id="lxor">lxor</em>                                 |*...,v1,v2 → ...,result*                  |                                                                                   |
| 0x84 |<em id="iinc">iinc,AA,+BB[^5]</em>                      |*...,v → ...,result*                      |                                                                                   |
| 0x85 |<em id="i2l">i2l</em>                                   |*...,v → ...,result*                      |                                                                                   |
| 0x86 |<em id="i2f">i2f</em>                                   |*...,v → ...,result*                      |                                                                                   |
| 0x87 |<em id="i2d">i2d</em>                                   |*...,v → ...,result*                      |                                                                                   |
| 0x88 |<em id="l2i">l2i</em>                                   |*...,v → ...,result*                      |                                                                                   |
| 0x89 |<em id="l2f">l2f</em>                                   |*...,v → ...,result*                      |                                                                                   |
| 0x8a |<em id="l2d">l2d</em>                                   |*...,v → ...,result*                      |                                                                                   |
| 0x8b |<em id="f2i">f2i</em>                                   |*...,v → ...,result*                      |                                                                                   |
| 0x8c |<em id="f2l">f2l</em>                                   |*...,v → ...,result*                      |                                                                                   |
| 0x8d |<em id="f2d">f2d</em>                                   |*...,v → ...,result*                      |                                                                                   |
| 0x8e |<em id="d2i">d2i</em>                                   |*...,v → ...,result*                      |                                                                                   |
| 0x8f |<em id="d2l">d2l</em>                                   |*...,v → ...,result*                      |                                                                                   |
| 0x90 |<em id="d2f">d2f</em>                                   |*...,v → ...,result*                      |                                                                                   |
| 0x91 |<em id="i2b">i2b</em>                                   |*...,v → ...,result*                      |                                                                                   |
| 0x92 |<em id="i2c">i2c</em>                                   |*...,v → ...,result*                      |                                                                                   |
| 0x93 |<em id="i2s">i2s</em>                                   |*...,v → ...,result*                      |                                                                                   |
| 0x94 |<em id="lcmp">lcmp</em>                                 |*...,v1,v2 → ...,result*                  |                                                                                   |
| 0x95 |<em id="fcmpl">fcmpl</em>                               |*...,v1,v2 → ...,result*                  |                                                                                   |
| 0x96 |<em id="fcmpg">fcmpg</em>                               |*...,v1,v2 → ...,result*                  |                                                                                   |
| 0x97 |<em id="dcmpl">dcmpl</em>                               |*...,v1,v2 → ...,result*                  |                                                                                   |
| 0x98 |<em id="dcmpg">dcmpg</em>                               |*...,v1,v2 → ...,result*                  |                                                                                   |
| 0x99 |<em id="ifeq">ifeq,+AAAA</em>                           |*...,v1,v2 → ...,result*                  |                                                                                   |
| 0x9a |<em id="ifne">ifne,+AAAA</em>                           |*...,v1,v2 → ...,result*                  |                                                                                   |
| 0x9b |<em id="iflt">iflt,+AAAA</em>                           |*...,v1,v2 → ...,result*                  |                                                                                   |
| 0x9c |<em id="ifge">ifge,+AAAA</em>                           |*...,v1,v2 → ...,result*                  |                                                                                   |
| 0x9d |<em id="ifgt">ifgt,+AAAA</em>                           |*...,v1,v2 → ...,result*                  |                                                                                   |
| 0x9e |<em id="ifle">ifle,+AAAA</em>                           |*...,v1,v2 → ...,result*                  |                                                                                   |
| 0x9f |<em id="if_icmpeq">if_icmpeq,+AAAA</em>                 |*...,v1,v2 → ...,result*                  |                                                                                   |
| 0xa7 |<em id="goto">goto,+AAAA</em>                           |                                          |                                                                                   |
| 0xa0 |<em id="if_icmpne">if_icmpne,+AAAA</em>                 |*...,v1,v2 → ...,result*                  |                                                                                   |
| 0xa1 |<em id="if_icmplt">if_icmplt,+AAAA</em>                 |*...,v1,v2 → ...,result*                  |                                                                                   |
| 0xa2 |<em id="if_icmpge">if_icmpge,+AAAA</em>                 |*...,v1,v2 → ...,result*                  |                                                                                   |
| 0xa3 |<em id="if_icmpgt">if_icmpgt,+AAAA</em>                 |*...,v1,v2 → ...,result*                  |                                                                                   |
| 0xa4 |<em id="if_icmple">if_icmple,+AAAA</em>                 |*...,v1,v2 → ...,result*                  |                                                                                   |
| 0xa5 |<em id="if_acmpeq">if_acmpeq,+AAAA</em>                 |*...,v1,v2 → ...,result*                  |                                                                                   |
| 0xa6 |<em id="if_acmpne">if_acmpne,+AAAA</em>                 |*...,v1,v2 → ...,result*                  |                                                                                   |
| 0xa8 |<em id="jsr">jsr,+AAAA</em>                             |*... → ...,address*                       |                                                                                   |
| 0xa9 |<em id="ret">ret,AA</em>                                |无变化                                    |                                                                                   |
| 0xaa |<em id="tableswitch">tableswitch<br>[0]{0,3}<br>+AAAAAAAA<br>+BBBBBBBB<br>+CCCCCCCC<br>{+DDDDDDDD..+NNNNNNNN}</em>  |*...,index → ...*|                                                |
| 0xab |<em id="lookupswitch">lookupswitch<br>[0]{0,3}<br>+AAAAAAAA<br>+BBBBBBBB<br>+CCCCCCCC<br>{+DDDDDDDD..+NNNNNNNN}</em>|*...,key → ...*  |                                                |
| 0xac |<em id="ireturn">ireturn</em>                           |*...,v → [empty]*                         |                                                                                   |
| 0xad |<em id="lreturn">lreturn</em>                           |*...,v → [empty]*                         |                                                                                   |
| 0xae |<em id="freturn">freturn</em>                           |*...,v → [empty]*                         |                                                                                   |
| 0xaf |<em id="dreturn">dreturn</em>                           |*...,v → [empty]*                         |                                                                                   |
| 0xb0 |<em id="areturn">areturn</em>                           |*...,v → [empty]*                         |                                                                                   |
| 0xb1 |<em id="return">return</em>                             |*...,v → [empty]*                         |                                                                                   |
| 0xb2 |<em id="getstatic">getstatic,AAAA</em>                  |*... → ...,v*                             |                                                                                   |
| 0xb3 |<em id="putstatic">putstatic,AAAA</em>                  |*... → ...,v*                             |                                                                                   |
| 0xb4 |<em id="getfield">getfield,AAAA</em>                    |*...,aref → ...,v*                        |                                                                                   |
| 0xb5 |<em id="putfield">putfield,AAAA</em>                    |*...,aref → ...,v*                        |                                                                                   |
| 0xb6 |<em id="invokevirtual">invokevirtual,AAAA</em>          |*...,aref,[arg1,[arg2...]] → ...*         |                                                                                   |
| 0xb7 |<em id="invokespecial">invokespecial,AAAA</em>          |*...,aref,[arg1,[arg2...]] → ...*         |                                                                                   |
| 0xb8 |<em id="invokestatic">invokestatic,AAAA</em>            |*...,[arg1,[arg2...]] → ...*              |                                                                                   |
| 0xb9 |<em id="invokeinterface">invokeinterface,AAAA,BB,00</em>|*...,aref,[arg1,[arg2...]] → ...*         |                                                                                   |
| 0xba |<em id="invokedynamic">invokedynamic,AAAA,00,00</em>    |*...,[arg1,[arg2...]] → ...*              |                                                                                   |
| 0xbb |<em id="new">new,AAAA</em>                              |*... → ...,aref*                          |                                                                                   |
| 0xbc |<em id="newarray">newarray,AA</em>                      |*...,count → ...,aaref*                   |                                                                                   |
| 0xbd |<em id="anewarray">anewarray,AAAA</em>                  |*...,count → ...,aaref*                   |                                                                                   |
| 0xbe |<em id="arraylength">arraylength</em>                   |*...,aaref → ...,length*                  |                                                                                   |
| 0xbf |<em id="athrow">athrow</em>                             |*...,aref → ...,aref*                     |                                                                                   |
| 0xc0 |<em id="checkcast">checkcast,AAAA</em>                  |*...,aref → ...,aref*                     |                                                                                   |
| 0xc1 |<em id="instanceof">instanceof,AAAA</em>                |*...,aref → ...,result*                   |                                                                                   |
| 0xc2 |<em id="monitorenter">monitorenter</em>                 |*...,aref → ...*                          |                                                                                   |
| 0xc3 |<em id="monitorexit">monitorexit</em>                   |*...,aref → ...*                          |                                                                                   |
| 0xc4 |<em id="wide">wide,&lt;opcode&gt;,AAAA,[BBBB]</em>      |同原指令                                  |                                                                                   |
| 0xc5 |<em id="multianewarray">multianewarray,AAAA,BB</em>     |*...,count1,[count2,...] → ...,aaref*     |                                                                                   |
| 0xc6 |<em id="ifnull">ifnull,+AAAA</em>                       |*...,v → ...*                             |                                                                                   |
| 0xc7 |<em id="ifnonnull">ifnonnull,+AAAA</em>                 |*...,v → ...*                             |                                                                                   |
| 0xc8 |<em id="goto_w">goto_w,+AAAAAAAA</em>                   |无变化                                    |                                                                                   |
| 0xc9 |<em id="jsr_w">jsr_w,+AAAAAAAA</em>                     |*... → ...,address*                       |                                                                                   |
| 0xca |<em id="breakpoint">breakpoint</em>                     |                                          | 为 *Java debugger 预留*                                                           |
| 0xcb |...                                                     |                                          | 预留                                                                              |
| ...  |...                                                     |                                          | 预留                                                                              |
| 0xfd |...                                                     |                                          | 预留                                                                              |
| 0xfe |*impdep1*                                               |                                          | 为 debugger 预留                                                                  |
| 0xff |*impdep2*                                               |                                          | 为 debugger 预留                                                                  |

----

[^1]: 用于存放操作数的栈结构，JVM 指令在执行的时候会从栈中取操作数，并将结果压回栈顶。栈还用于存放方法的参数（非静态方法的第一个参数是 *this* 引用），以及方法返回的结果。
[^2]: *AA* 表示 1 个无符号字节 *(unsighed byte)*
[^3]: 直接编码在指令中并作为操作数使用的数据，如：`bipush 0x10`，`0x10` 被直接编码进指令序列中，即为立即数。
[^4]: *AAAA* 表示 1 个无符号 16 位整型 *(unsighed 16-bit int)*
[^5]: *+BB* 表示 1 个有符号字节 *(signed byte)*
